{"meta":{"title":"Prov\u00e9rbios","abbrev":"pv"},"chapter":6,"content":{"1":"Meu filho, se voc\u00ea foi fiador do seu pr\u00f3ximo, e fez acordo com algum estrangeiro;","2":"se voc\u00ea se comprometeu, dando sua palavra, e ficou preso pelo que disse,","3":"voc\u00ea caiu em poder do seu pr\u00f3ximo. Para se livrar, fa\u00e7a o seguinte, meu filho:","4":"V\u00e1, insista e incomode o seu pr\u00f3ximo. N\u00e3o durma, nem descanse.","5":"Liberte-se, como a cerva da armadilha ou o passarinho da arapuca.","6":"Vamos, pregui\u00e7oso, olhe a formiga, observe os h\u00e1bitos dela, e aprenda.","7":"Ela n\u00e3o tem chefe, nem guia, nem governante.","8":"Apesar disso, no ver\u00e3o ela acumula o gr\u00e3o e ajunta provis\u00f5es durante a colheita.","9":"At\u00e9 quando voc\u00ea vai ficar dormindo, pregui\u00e7oso? Quando \u00e9 que vai se levantar da cama?","10":"Dormindo um pouco, cochilando outro pouco e mais um pouco ainda, cruzando os bra\u00e7os e descansando,","11":"sobre voc\u00ea cair\u00e1 a pobreza do vagabundo e a indig\u00eancia do mendigo.","12":"O homem falso e malfeitor emprega palavras enganadoras,","13":"pisca o olho, balan\u00e7a os p\u00e9s e faz sinal com os dedos;","14":"pensa em desatinos, planeja maldades e est\u00e1 sempre semeando disc\u00f3rdia.","15":"Mas, de repente, cai sobre ele a perdi\u00e7\u00e3o e, num instante, o quebra sem rem\u00e9dio.","16":"Jav\u00e9 detesta seis coisas, e a s\u00e9tima ele abomina:","17":"olhos altivos, l\u00edngua mentirosa, m\u00e3os que derramam sangue inocente,","18":"cora\u00e7\u00e3o que maquina planos perversos, p\u00e9s que correm para a maldade,","19":"testemunha falsa que profere mentiras, e aquele que semeia disc\u00f3rdia entre irm\u00e3os.","20":"Meu filho, guarde os preceitos de seu pai e n\u00e3o despreze o ensinamento de sua m\u00e3e.","21":"Conserve-os sempre vivos na mem\u00f3ria e amarre-os no pesco\u00e7o.","22":"Desse modo, quando voc\u00ea caminhar, eles o guiar\u00e3o; quando voc\u00ea descansar, eles o guardar\u00e3o; e quando voc\u00ea despertar, eles falar\u00e3o com voc\u00ea.","23":"Porque o preceito \u00e9 uma l\u00e2mpada, a instru\u00e7\u00e3o \u00e9 uma luz e a repreens\u00e3o que corrige \u00e9 caminho de vida.","24":"Eles proteger\u00e3o voc\u00ea da mulher m\u00e1 e da l\u00edngua suave da estrangeira.","25":"Que seu cora\u00e7\u00e3o n\u00e3o cobice a beleza dela, nem se deixe prender por seus olhares.","26":"A prostituta procura um peda\u00e7o de p\u00e3o, mas a mulher casada vai \u00e0 ca\u00e7a de uma vida.","27":"Pode algu\u00e9m carregar fogo no peito sem queimar a pr\u00f3pria roupa?","28":"Pode algu\u00e9m caminhar em cima de brasas e n\u00e3o queimar os pr\u00f3prios p\u00e9s?","29":"O mesmo acontece com aquele que procura a mulher do pr\u00f3ximo: quem a toca, n\u00e3o ficar\u00e1 sem castigo.","30":"O ladr\u00e3o n\u00e3o fica difamado quando rouba para matar a fome;","31":"se o prendem, ele dever\u00e1 devolver sete vezes mais e entregar todos os bens de sua casa.","32":"Mas o ad\u00faltero n\u00e3o tem bom senso: s\u00f3 age assim quem quer se arruinar.","33":"Levar\u00e1 uma surra, passar\u00e1 vergonha, e sua inf\u00e2mia nunca desaparecer\u00e1.","34":"Porque o ci\u00fame provocar\u00e1 a raiva do marido, que n\u00e3o ter\u00e1 piedade no dia da vingan\u00e7a:","35":"de nenhum modo aceitar\u00e1 compensa\u00e7\u00e3o, e recusar\u00e1 pagamento, mesmo que seja grande."}}