{"meta":{"title":"Lamenta\u00e7\u00f5es de Jeremias","abbrev":"lm"},"chapter":1,"content":{"1":"Como jaz solit\u00e1ria a cidade outrora populosa!","2":"Chora e chora de noite,","3":"Jud\u00e1 foi levado ao ex\u00edlio,","4":"Os caminhos de Si\u00e3o est\u00e3o de luto,","5":"Os seus advers\u00e1rios triunfam,","6":"Da filha de Si\u00e3o j\u00e1 se passou","7":"Agora, nos dias da sua afli\u00e7\u00e3o e do seu desterro,","8":"Jerusal\u00e9m pecou gravemente;","9":"A sua imund\u00edcia est\u00e1 nas suas saias;","10":"Estendeu o advers\u00e1rio a m\u00e3o","11":"Todo o seu povo anda gemendo","12":"N\u00e3o vos comove isto, a todos v\u00f3s que passais pelo caminho?","13":"L\u00e1 do alto enviou fogo a meus ossos,","14":"O jugo das minhas transgress\u00f5es","15":"O Senhor dispersou todos os valentes","16":"Por estas coisas, choro eu;","17":"Estende Si\u00e3o as m\u00e3os,","18":"Justo \u00e9 o Senhor ,","19":"Chamei os meus amigos,","20":"Olha, Senhor , porque estou angustiada;","21":"Ouvem que eu suspiro,","22":"Venha toda a sua iniquidade"},"titles":{"1":"Jerusal\u00e9m destru\u00edda e desolada"}}