{"meta":{"title":"Descida de Cristo ao Inferno","abbrev":"descida-cristo-inferno"},"chapter":3,"content":{"1":"Ao ouvir o primeiro a ser criado e pai de todos a instru\u00e7\u00e3o que Jo\u00e3o estava dando aos que se encontravam no inferno, disse Ad\u00e3o ao seu filho Seth: \u201cMeu filho, quero que digas aos pais do g\u00eanero humano e aos profetas para onde eu o enviei quando ca\u00ed no transe da morte\u201d. Seth disse: \u201cProfetas e patriarcas, escutai: meu pai Ad\u00e3o, a primeira das criaturas, caiu uma vez em perigo de morte e enviou-me para fazer ora\u00e7\u00f5es a Deus muito pr\u00f3ximo da porta do para\u00edso, para que me fizesse chegar por meio de um anjo at\u00e9 a \u00e1rvore da miseric\u00f3rdia, de onde haveria de tomar do \u00f3leo, para com ele ungir meu pai para que assim ele pudesse recuperar-se de sua doen\u00e7a. Assim fiz. E, depois de fazer minha ora\u00e7\u00e3o, um anjo do Senhor veio e disse-me: \u2018Que pedes, Seth? Buscas o \u00f3leo que cura os doentes ou a \u00e1rvore que o distila para a doen\u00e7a do teu pai? Isto n\u00e3o pode ser encontrado agora. Vai, pois, e diz ao teu pai que depois de cinco mil e quinhentos anos, a partir da cria\u00e7\u00e3o do mundo,haver\u00e1 de descer o Filho de Deus humanizado; Ele encarregar-se-\u00e1 de ungi-lo com este \u00f3leo, e teu pai levantar-se-\u00e1; e, al\u00e9m disso, purifica-lo-\u00e1, tanto a ele quanto aos seus descendentes com \u00e1gua e com o Esp\u00edrito Santo; e ent\u00e3o, sim, ver-se-\u00e1 curado de todas as doen\u00e7as, por\u00e9m, por agora, isto \u00e9 imposs\u00edvel\u2019.\u201d","2":"Os patriarcas e profetas que ouviram isto alegraram-se grandemente."}}