{"meta":{"title":"Prov\u00e9rbios","abbrev":"pv"},"chapter":5,"content":{"1":"Filho meu, atende a minha sabedoria; \u00e0 minha intelig\u00eancia inclina os ouvidos","2":"para que conserves a discri\u00e7\u00e3o, e os teus l\u00e1bios guardem o conhecimento;","3":"porque os l\u00e1bios da mulher ad\u00faltera destilam favos de mel, e as suas palavras s\u00e3o mais suaves do que o azeite;","4":"mas o fim dela \u00e9 amargoso como o absinto, agudo, como a espada de dois gumes.","5":"Os seus p\u00e9s descem \u00e0 morte; os seus passos conduzem-na ao inferno.","6":"Ela n\u00e3o pondera a vereda da vida; anda errante nos seus caminhos e n\u00e3o o sabe.","7":"Agora, pois, filho, d\u00e1-me ouvidos e n\u00e3o te desvies das palavras da minha boca.","8":"Afasta o teu caminho da mulher ad\u00faltera e n\u00e3o te aproximes da porta da sua casa;","9":"para que n\u00e3o d\u00eas a outrem a tua honra, nem os teus anos, a cru\u00e9is;","10":"para que dos teus bens n\u00e3o se fartem os estranhos, e o fruto do teu trabalho n\u00e3o entre em casa alheia;","11":"e gemas no fim de tua vida, quando se consumirem a tua carne e o teu corpo,","12":"e digas: Como aborreci o ensino! E desprezou o meu cora\u00e7\u00e3o a disciplina!","13":"E n\u00e3o escutei a voz dos que me ensinavam, nem a meus mestres inclinei os ouvidos!","14":"Quase que me achei em todo mal que sucedeu no meio da assembleia e da congrega\u00e7\u00e3o.","15":"Bebe a \u00e1gua da tua pr\u00f3pria cisterna e das correntes do teu po\u00e7o.","16":"Derramar-se-iam por fora as tuas fontes, e, pelas pra\u00e7as, os ribeiros de \u00e1guas?","17":"Sejam para ti somente e n\u00e3o para os estranhos contigo.","18":"Seja bendito o teu manancial, e alegra-te com a mulher da tua mocidade,","19":"cor\u00e7a de amores e gazela graciosa. Saciem-te os seus seios em todo o tempo; e embriaga-te sempre com as suas car\u00edcias.","20":"Por que, filho meu, andarias cego pela estranha e abra\u00e7arias o peito de outra?","21":"Porque os caminhos do homem est\u00e3o perante os olhos do Senhor , e ele considera todas as suas veredas.","22":"Quanto ao perverso, as suas iniquidades o prender\u00e3o, e com as cordas do seu pecado ser\u00e1 detido.","23":"Ele morrer\u00e1 pela falta de disciplina, e, pela sua muita loucura, perdido, cambaleia."},"titles":{"1":"Advert\u00eancia contra a lasc\u00edvia"}}