{"meta":{"title":"Deuteron\u00f4mio","abbrev":"dt"},"chapter":14,"content":{"1":"Ye","2":"For thou","3":"Thou shalt not eat any abominable thing.","4":"These","5":"The hart, and the roebuck, and the fallow deer, and the wild goat, and the pygarg, and the wild ox, and the chamois.","6":"And every beast that parteth the hoof, and cleaveth the cleft into two claws,","7":"Nevertheless these ye shall not eat of them that chew the cud, or of them that divide the cloven hoof;","8":"And the swine, because it divideth the hoof, yet cheweth not the cud, it","9":"These ye shall eat of all that","10":"And whatsoever hath not fins and scales ye may not eat; it","11":"Of","12":"But these","13":"And the glede, and the kite, and the vulture after his kind,","14":"And every raven after his kind,","15":"And the owl, and the night hawk, and the cuckow, and the hawk after his kind,","16":"The little owl, and the great owl, and the swan,","17":"And the pelican, and the gier eagle, and the cormorant,","18":"And the stork, and the heron after her kind, and the lapwing, and the bat.","19":"And every creeping thing that flieth","20":"But of","21":"Ye shall not eat","22":"Thou shalt truly tithe all the increase of thy seed, that the field bringeth forth year by year.","23":"And thou shalt eat before the","24":"And if the way be too long for thee, so that thou art not able to carry it;","25":"Then shalt thou turn","26":"And thou shalt bestow that money for whatsoever thy soul lusteth after, for oxen, or for sheep, or for wine, or for strong drink, or for whatsoever thy soul desireth: and thou shalt eat there before the","27":"And the Levite that","28":"At the end of three years thou shalt bring forth all the tithe of thine increase the same year, and shalt lay","29":"And the Levite, (because he hath no part nor inheritance with thee,) and the stranger, and the fatherless, and the widow, which"}}