{"meta":{"title":"Prov\u00e9rbios","abbrev":"pv"},"chapter":21,"content":{"1":"21 O cora\u00e7\u00e3o do rei \u00e9 como correntes de \u00e1gua nas m\u00e3os de Jeov\u00e1. Ele o direciona para onde quiser.","2":"O homem pensa que todos os seus caminhos s\u00e3o certos, Mas Jeov\u00e1 examina os cora\u00e7\u00f5es.","3":"Fazer o que \u00e9 correto e justo \u00c9 mais agrad\u00e1vel a Jeov\u00e1 do que um sacrif\u00edcio.","4":"Olhos arrogantes e um cora\u00e7\u00e3o orgulhoso; A l\u00e2mpada que guia os maus \u00e9 o pecado.","5":"Os planos do diligente certamente d\u00e3o bons resultados, Mas todos os precipitados acabar\u00e3o na pobreza.","6":"Tesouros obtidos com uma l\u00edngua mentirosa S\u00e3o como uma neblina passageira, uma armadilha mortal.","7":"A viol\u00eancia dos maus os destruir\u00e1, Pois eles se negam a praticar a justi\u00e7a.","8":"O caminho do homem culpado \u00e9 tortuoso, Mas as a\u00e7\u00f5es do homem puro s\u00e3o retas.","9":"Melhor morar num canto do terra\u00e7o Do que com uma esposa briguenta, na mesma casa.","10":"O homem perverso anseia o que \u00e9 mau; Ele n\u00e3o mostra favor ao seu pr\u00f3ximo.","11":"Quando o zombador \u00e9 punido, o inexperiente obt\u00e9m sabedoria; Quando o s\u00e1bio recebe instru\u00e7\u00e3o, obt\u00e9m conhecimento.","12":"O Justo observa a casa de quem \u00e9 mau, E faz os maus cair na ru\u00edna.","13":"Quem tapa o ouvido ao clamor do pobre, Tamb\u00e9m clamar\u00e1 e n\u00e3o ter\u00e1 resposta.","14":"Um presente dado em segredo abranda a ira; E o suborno dado \u00e0s escondidas, o forte furor.","15":"Agir com justi\u00e7a \u00e9 uma alegria para o justo, Mas \u00e9 algo terr\u00edvel para os que praticam a maldade.","16":"O homem que se desvia do caminho do entendimento Descansar\u00e1 na companhia dos impotentes na morte.","17":"Quem ama a divers\u00e3o ficar\u00e1 pobre; Quem ama o vinho e o azeite n\u00e3o ficar\u00e1 rico.","18":"O perverso serve de resgate para o justo; E o trai\u00e7oeiro, para os \u00edntegros.","19":"Melhor morar no deserto Do que com uma esposa briguenta e geniosa.","20":"H\u00e1 tesouro precioso e azeite na casa do s\u00e1bio, Mas o tolo desperdi\u00e7a o que tem.","21":"Quem se empenha pela justi\u00e7a e pelo amor leal Achar\u00e1 vida, justi\u00e7a e gl\u00f3ria.","22":"O s\u00e1bio pode escalar a muralha da cidade dos valentes E minar a for\u00e7a em que eles confiam.","23":"Quem vigia sua boca e sua l\u00edngua Fica livre de problemas.","24":"Chama-se de zombador presun\u00e7oso e arrogante Quem age com excessiva presun\u00e7\u00e3o.","25":"O desejo do pregui\u00e7oso o matar\u00e1, Pois suas m\u00e3os se negam a trabalhar.","26":"Ele passa o dia desejando avidamente, Mas o justo d\u00e1 sem reservas.","27":"O sacrif\u00edcio dos maus \u00e9 detest\u00e1vel. Quanto mais quando o oferecem com m\u00e1s inten\u00e7\u00f5es!","28":"A testemunha mentirosa morrer\u00e1, Mas o homem que sabe escutar ser\u00e1 bem-sucedido em seu testemunho.","29":"O perverso mostra no rosto a sua insol\u00eancia, Mas \u00e9 o justo que tem o caminho seguro.","30":"N\u00e3o h\u00e1 sabedoria, nem discernimento, nem conselho que possam se opor a Jeov\u00e1.","31":"O cavalo \u00e9 preparado para o dia da batalha, Mas a salva\u00e7\u00e3o pertence a Jeov\u00e1."}}