{"meta":{"title":"J\u00f3","abbrev":"j\u00f3"},"chapter":3,"content":{"1":"Enfim, J\u00f3 abriu a boca e amaldi\u00e7oou o dia de seu nascimento;","2":"come\u00e7ou a dizer:","3":"Pere\u00e7a o dia em que nascie a noite em que se disse: \u201cFoi concebido um homem!\u201d","4":"Aquele dia seja trevas,n\u00e3o cuide dele Deus l\u00e1 do alto,nem brilhe sobre ele a luz.","5":"Apoderem-se dele as trevas e a sombra da morte,uma nuvem se estenda sobre elee a escurid\u00e3o do dia o apavore!","6":"O escuro domine aquela noite,n\u00e3o seja ela contada entre os dias do ano,nem entre na conta dos meses.","7":"Aquela noite seja est\u00e9rile nela n\u00e3o entre o som do j\u00fabilo;","8":"Que lhe lancem maldi\u00e7\u00f5es os que amaldi\u00e7oam o dia,os que sabem evocar Leviat\u00e3.","9":"Escure\u00e7am as estrelas de sua aurora;que espere a luz e n\u00e3o venha;n\u00e3o veja abrir-se os olhos da alvorada,","10":"porque n\u00e3o fechou a porta do ventre de minha m\u00e3e,e n\u00e3o escondeu de meus olhos a mis\u00e9ria!","11":"Por que n\u00e3o morri ao nascere n\u00e3o pereci logo que sa\u00ed do ventre?","12":"Por que dois joelhos me acolherame dois seios me amamentaram?","13":"Sim, agora eu repousaria tranquilo,dormiria e teria descanso","14":"com os reis e os conselheiros da terra,que para si constru\u00edram mausol\u00e9us;","15":"ou com os pr\u00edncipes, que t\u00eam ouroe enchem de prata suas casas.","16":"Ou, como aborto oculto, eu n\u00e3o existiria,como os fetos que n\u00e3o viram a luz.","17":"L\u00e1 embaixo os maus param de atormentare repousa quem se cansou.","18":"Os prisioneiros descansam juntos,n\u00e3o ouvem mais a voz do opressor.","19":"L\u00e1 est\u00e3o o pequeno e o grande,e o escravo est\u00e1 livre de seu patr\u00e3o.","20":"Para que dar luz a um infelize vida a quem tem amargura no cora\u00e7\u00e3o,","21":"\u00e0queles que esperam a morte e ela n\u00e3o vem,e a procuram mais que a um tesouro,","22":"que se alegram exultantese rejubilam ao encontrar a sepultura...","23":"a um homem, cujo caminho \u00e9 ocultoe a quem Deus de todo lado cercou?","24":"Em lugar da comida tenho meu gemido,e meus clamores se derramam como \u00e1gua,","25":"porque o que eu temo me acontecee o que me espanta me atinge.","26":"N\u00e3o tenho paz, n\u00e3o tenho descanso,n\u00e3o tenho repouso, me assalta o tormento!"},"titles":{}}