{"meta":{"title":"J\u00f3","abbrev":"j\u00f3"},"chapter":8,"content":{"1":"Ent\u00e3o come\u00e7ou a dizer Baldad de Su\u00e1s:","2":"At\u00e9 quando falar\u00e1s desse modo e tuas palavras ser\u00e3o como um vento impetuoso?","3":"Pode Deus desviar o direito? Pode o Onipotente subverter a justi\u00e7a?","4":"Se teus filhos pecaram contra ele, entregou-os ao poder da iniquidade deles.","5":"Se buscares a Deus e implorares ao Onipotente,","6":"se \u00e9s puro e \u00edntegro, desde agora velar\u00e1 sobre ti e restabelecer\u00e1 a morada de tua justi\u00e7a.","7":"Tua primitiva condi\u00e7\u00e3o ser\u00e1 pouca coisa diante de teu magn\u00edfico futuro.","8":"Pergunta \u00e0s gera\u00e7\u00f5es passadas, reflete na experi\u00eancia de seus pais,","9":"porque n\u00f3s somos de ontem e nada sabemos, passam como sombra nossos dias na terra.","10":"Mas eles te instruir\u00e3o e te falar\u00e3o, trazendo do cora\u00e7\u00e3o as palavras.","11":"Cresce o papiro fora do p\u00e2ntano? Pode brotar o junco sem \u00e1gua?","12":"Quando est\u00e1 verde e ainda n\u00e3o cortado, seca antes de qualquer outra planta.","13":"Tal \u00e9 o destino de quem se esquece de Deus; assim se frustra a esperan\u00e7a do \u00edmpio.","14":"Sua confian\u00e7a \u00e9 como um fio, e uma teia de aranha \u00e9 sua seguran\u00e7a:","15":"Ele se apoia em sua casa, mas ela n\u00e3o resiste; agarra-se nela, mas ela n\u00e3o aguenta.","16":"\u00c9 \u00e1rvore vi\u00e7osa diante do sol, e sobre o jardim se expandem seus ramos,","17":"sobre um mont\u00e3o de pedras se entrela\u00e7am suas ra\u00edzes, explora as fendas das rochas.","18":"Mas se \u00e9 tirado de seu lugar, este o renega: \u201cNunca te vi!\u201d","19":"Esta \u00e9 a alegria de sua vida, e da terra brotam outros.","20":"N\u00e3o, Deus n\u00e3o rejeita o homem \u00edntegro nem colabora com os malfeitores.","21":"Encher\u00e1 de novo tua boca de sorrisos e teus l\u00e1bios de cantos de alegria.","22":"Teus inimigos ser\u00e3o cobertos de vergonha, e a tenda dos \u00edmpios n\u00e3o mais existir\u00e1."},"titles":{}}