{"meta":{"title":"J\u00f3","abbrev":"j\u00f3"},"chapter":26,"content":{"1":"J\u00f3, por\u00e9m, respondeu:","2":"Como sabes ajudar ao que n\u00e3o tem for\u00e7a","3":"Como sabes aconselhar ao que n\u00e3o tem sabedoria","4":"Com a ajuda de quem proferes tais palavras?","5":"A alma dos mortos treme","6":"O al\u00e9m est\u00e1 desnudo perante ele,","7":"Ele estende o norte sobre o vazio","8":"Prende as \u00e1guas em densas nuvens,","9":"Encobre a face do seu trono","10":"Tra\u00e7ou um c\u00edrculo \u00e0 superf\u00edcie das \u00e1guas,","11":"As colunas do c\u00e9u tremem","12":"Com a sua for\u00e7a fende o mar","13":"Pelo seu sopro aclara os c\u00e9us,","14":"Eis que isto s\u00e3o apenas as orlas dos seus caminhos!"},"titles":{"1":"J\u00f3 afirma a soberania de Deus"}}