{"meta":{"title":"J\u00f3","abbrev":"j\u00f3"},"chapter":34,"content":{"1":"Disse mais Eli\u00fa:","2":"Ouvi, \u00f3 s\u00e1bios, as minhas raz\u00f5es;","3":"Porque o ouvido prova as palavras,","4":"O que \u00e9 direito escolhamos para n\u00f3s;","5":"Porque J\u00f3 disse: Sou justo,","6":"Apesar do meu direito, sou tido por mentiroso;","7":"Que homem h\u00e1 como J\u00f3,","8":"E anda em companhia dos que praticam a iniquidade","9":"Pois disse: De nada aproveita ao homem","10":"Pelo que v\u00f3s, homens sensatos, escutai-me:","11":"Pois retribui ao homem segundo as suas obras","12":"Na verdade, Deus n\u00e3o procede maliciosamente;","13":"Quem lhe entregou o governo da terra?","14":"Se Deus pensasse apenas em si mesmo","15":"toda a carne juntamente expiraria,","16":"Se, pois, h\u00e1 em ti entendimento, ouve isto;","17":"Acaso, governaria o que aborrecesse o direito?","18":"Dir-se-\u00e1 a um rei: Oh! Vil?","19":"Quanto menos \u00e0quele que n\u00e3o faz acep\u00e7\u00e3o das pessoas de pr\u00edncipes,","20":"De repente, morrem;","21":"Os olhos de Deus est\u00e3o sobre os caminhos do homem","22":"N\u00e3o h\u00e1 trevas nem sombra assaz profunda,","23":"Pois Deus n\u00e3o precisa observar por muito tempo o homem","24":"Quebranta os fortes, sem os inquirir,","25":"Ele conhece, pois, as suas obras;","26":"Ele os fere como a perversos,","27":"porque dele se desviaram,","28":"e, assim, fizeram que o clamor do pobre subisse at\u00e9 Deus,","29":"Se ele aquietar-se, quem o condenar\u00e1?","30":"Para que o \u00edmpio n\u00e3o reine,","31":"Se algu\u00e9m diz a Deus:","32":"o que n\u00e3o vejo, ensina-mo tu;","33":"acaso, deve ele recompensar-te segundo tu queres ou n\u00e3o queres?","34":"Os homens sensatos dir-me-\u00e3o,","35":"J\u00f3 falou sem conhecimento,","36":"Tomara fosse J\u00f3 provado at\u00e9 ao fim,","37":"Pois ao seu pecado acrescenta rebeli\u00e3o,"},"titles":{"1":"Eli\u00fa justifica a Deus"}}