{"meta":{"title":"J\u00f3","abbrev":"j\u00f3"},"chapter":37,"content":{"1":"Sobre isto treme tamb\u00e9m o meu cora\u00e7\u00e3o","2":"Dai ouvidos ao trov\u00e3o de Deus,","3":"ele o solta por debaixo de todos os c\u00e9us,","4":"Depois deste, ruge a sua voz,","5":"Com a sua voz troveja Deus maravilhosamente;","6":"Porque ele diz \u00e0 neve: Cai sobre a terra;","7":"Assim, torna ele inativas as m\u00e3os de todos os homens,","8":"E as alim\u00e1rias entram nos seus esconderijos","9":"De suas rec\u00e2maras sai o p\u00e9 de vento,","10":"Pelo sopro de Deus se d\u00e1 a geada,","11":"Tamb\u00e9m de umidade carrega as densas nuvens,","12":"Ent\u00e3o, elas, segundo o rumo que ele d\u00e1,","13":"E tudo isso faz ele vir para disciplina,","14":"Inclina, J\u00f3, os ouvidos a isto,","15":"Porventura, sabes tu como Deus as opera","16":"Tens tu not\u00edcia do equil\u00edbrio das nuvens","17":"Que faz aquecer as tuas vestes,","18":"Ou estendeste com ele o firmamento,","19":"Ensina-nos o que lhe diremos;","20":"Contar-lhe-ia algu\u00e9m o que tenho dito?","21":"Eis que o homem n\u00e3o pode olhar para o sol,","22":"Do norte vem o \u00e1ureo esplendor,","23":"Ao Todo-Poderoso, n\u00e3o o podemos alcan\u00e7ar;","24":"Por isso, os homens o temem;"}}