{"meta":{"title":"Salmos","abbrev":"sl"},"chapter":29,"content":{"1":"Salmo de Davi. Dai ao SENHOR, \u00f3 v\u00f3s poderosos, dai ao SENHOR gl\u00f3ria e for\u00e7a.","2":"Dai ao SENHOR a gl\u00f3ria devida ao seu nome; adorai o SENHOR na beleza da santidade.","3":"A voz do SENHOR est\u00e1 sobre as \u00e1guas; o Deus da gl\u00f3ria troveja; o SENHOR est\u00e1 sobre as muitas \u00e1guas.","4":"A voz do SENHOR \u00e9 poderosa; a voz do SENHOR \u00e9 cheia de majestade.","5":"A voz do SENHOR quebra os cedros; sim, o SENHOR quebra os cedros do L\u00edbano.","6":"Ele tamb\u00e9m os faz saltar como um novilho; o L\u00edbano e Siriom como um unic\u00f3rnio jovem.","7":"A voz do SENHOR divide as chamas do fogo.","8":"A voz do SENHOR estremece o deserto; o SENHOR sacode o deserto de Cades.","9":"A voz do SENHOR faz com que as cor\u00e7as deem cria, e descobre as florestas; e no seu templo todos falam da sua gl\u00f3ria.","10":"O SENHOR est\u00e1 assentado sobre o dil\u00favio; Sim, o SENHOR est\u00e1 sentado como Rei para sempre.","11":"O SENHOR dar\u00e1 for\u00e7a ao seu povo; o SENHOR aben\u00e7oar\u00e1 o seu povo com a paz."}}