{"meta":{"title":"J\u00f3","abbrev":"j\u00f3"},"chapter":22,"content":{"1":"Elifaz de Tem\u00e3 tomou a palavra e disse:","2":"\u201cPor acaso pode o homem ser \u00fatil a Deus, uma vez que o s\u00e1bio s\u00f3 pode no m\u00e1ximo ajudar a si pr\u00f3prio?","3":"O que importa ao Todo-poderoso se voc\u00ea \u00e9 justo? O que ele ganha, se voc\u00ea \u00e9 \u00edntegro?","4":"Ser\u00e1 que \u00e9 por causa da fidelidade de voc\u00ea que ele o reprova, ou convoca voc\u00ea para o julgamento?","5":"N\u00e3o ser\u00e1 antes pela sua grande maldade e pelas suas incont\u00e1veis culpas?","6":"De fato, voc\u00ea penhorava os bens de seus irm\u00e3os e despojava os outros at\u00e9 deix\u00e1-los nus.","7":"Voc\u00ea n\u00e3o oferecia \u00e1gua ao sedento, e negava p\u00e3o ao faminto.","8":"Voc\u00ea entregava a terra aos poderosos, e a\u00ed se instalavam os privilegiados.","9":"Voc\u00ea despedia as vi\u00favas de m\u00e3os vazias, e violava o direito dos \u00f3rf\u00e3os.","10":"\u00c9 por isso que voc\u00ea est\u00e1 preso nos la\u00e7os e perturbado por terrores fulminantes.","11":"A escurid\u00e3o n\u00e3o deixa voc\u00ea enxergar; e voc\u00ea est\u00e1 coberto pela enchente das \u00e1guas.","12":"Ser\u00e1 que Deus n\u00e3o est\u00e1 no mais alto do c\u00e9u? Veja bem como \u00e9 alto o arco do c\u00e9u estrelado!","13":"E voc\u00ea ainda diz: \u2018O que sabe Deus? Ser\u00e1 que ele \u00e9 capaz de distinguir atrav\u00e9s das nuvens escuras?","14":"As nuvens s\u00e3o como v\u00e9u e o impedem de ver, enquanto ele passeia pelo firmamento do c\u00e9u\u2019.","15":"Por acaso voc\u00ea quer seguir o antigo caminho batido por homens perversos,","16":"arrastados antes do tempo, quando a enchente de um rio desmoronou seus alicerces?","17":"Eles diziam a Deus: \u2018Afasta-te de n\u00f3s. O que pode o Todo-poderoso fazer contra n\u00f3s?\u2019","18":"Deus tinha enchido de bens a casa deles, e eles o exclu\u00edam de seus projetos perversos.","19":"Os justos agora veem e se alegram, e os inocentes zombam deles:","20":"\u2018Acabaram as riquezas deles! O fogo devorou o que haviam ganhado!\u2019","21":"Vamos, reconcilie-se e fa\u00e7a as pazes com Deus. E voc\u00ea vai ser novamente feliz.","22":"Aceite a instru\u00e7\u00e3o da boca de Deus e guarde no cora\u00e7\u00e3o as palavras dele.","23":"Se voc\u00ea voltar para o Todo-poderoso, ele o restabelecer\u00e1. Afaste a injusti\u00e7a de sua tenda,","24":"jogue seu ouro ao p\u00f3, e o ouro de Ofir entre as pedras do rio.","25":"Ent\u00e3o o Todo-poderoso ser\u00e1 o seu ouro, e tamb\u00e9m prata aos montes.","26":"Ent\u00e3o voc\u00ea se alegrar\u00e1 com o Todo-poderoso, e erguer\u00e1 o rosto para Deus.","27":"Ele ouvir\u00e1 as suas s\u00faplicas, e voc\u00ea cumprir\u00e1 o que havia prometido.","28":"Voc\u00ea far\u00e1 um projeto, que se realizar\u00e1, e a luz brilhar\u00e1 em seu caminho.","29":"Porque ele humilha os arrogantes e salva os que se humilham.","30":"Ele liberta o homem inocente, e voc\u00ea ser\u00e1 salvo pela pureza de suas pr\u00f3prias m\u00e3os\u201d."}}