{"meta":{"title":"Salmos","abbrev":"sl"},"chapter":135,"content":{"1":"Aleluia!","2":"v\u00f3s que assistis na Casa do Senhor ,","3":"Louvai ao Senhor , porque o Senhor \u00e9 bom;","4":"Pois o Senhor escolheu para si a Jac\u00f3","5":"Com efeito, eu sei que o Senhor \u00e9 grande","6":"Tudo quanto aprouve ao Senhor , ele o fez,","7":"Faz subir as nuvens dos confins da terra,","8":"Foi ele quem feriu os primog\u00eanitos no Egito,","9":"quem, no meio de ti, \u00f3 Egito, operou sinais e prod\u00edgios","10":"quem feriu muitas na\u00e7\u00f5es","11":"a Seom, rei dos amorreus,","12":"cujas terras deu em heran\u00e7a,","13":"O teu nome, Senhor , subsiste para sempre;","14":"Pois o Senhor julga ao seu povo","15":"Os \u00eddolos das na\u00e7\u00f5es s\u00e3o prata e ouro,","16":"T\u00eam boca e n\u00e3o falam;","17":"t\u00eam ouvidos e n\u00e3o ouvem;","18":"Como eles se tornam os que os fazem,","19":"Casa de Israel, bendizei ao Senhor ;","20":"casa de Levi, bendizei ao Senhor ;","21":"Desde Si\u00e3o bendito seja o Senhor ,"},"titles":{"1":"Louvores a Deus"}}