{"meta":{"title":"Salmos","abbrev":"sl"},"chapter":34,"content":{"1":"Bendirei o Senhor em todo o tempo,","2":"Gloriar-se-\u00e1 no Senhor a minha alma;","3":"Engrandecei o Senhor comigo,","4":"Busquei o Senhor , e ele me acolheu;","5":"Contemplai-o e sereis iluminados,","6":"Clamou este aflito, e o Senhor o ouviu","7":"O anjo do Senhor acampa-se","8":"Oh! Provai e vede que o Senhor \u00e9 bom;","9":"Temei o Senhor , v\u00f3s os seus santos,","10":"Os le\u00f5ezinhos sofrem necessidade e passam fome,","11":"Vinde, filhos, e escutai-me;","12":"Quem \u00e9 o homem que ama a vida","13":"Refreia a l\u00edngua do mal","14":"Aparta-te do mal e pratica o que \u00e9 bom;","15":"Os olhos do Senhor repousam sobre os justos,","16":"O rosto do Senhor est\u00e1 contra os que praticam o mal,","17":"Clamam os justos, e o Senhor os escuta","18":"Perto est\u00e1 o Senhor dos que t\u00eam o cora\u00e7\u00e3o quebrantado","19":"Muitas s\u00e3o as afli\u00e7\u00f5es do justo,","20":"Preserva-lhe todos os ossos,","21":"O infort\u00fanio matar\u00e1 o \u00edmpio,","22":"O Senhor resgata a alma dos seus servos,"},"titles":{"1":"Salmo de Davi, quando se fingiu amalucado na presen\u00e7a de Abimeleque e, por este expulso, ele se foi"}}